convexgeometry/__init__.py
convexgeometry/walks.py
convexgeometry-0.0.2.dist-info/LICENSE
convexgeometry-0.0.2.dist-info/METADATA
convexgeometry-0.0.2.dist-info/WHEEL
convexgeometry-0.0.2.dist-info/top_level.txt
convexgeometry-0.0.2.dist-info/RECORD
