Metadata-Version: 2.1
Name: convexgeometry
Version: 0.0.2
Summary: A collection of algorithms for membership and sampling of convex sets
Home-page: https://github.com/jtanderson/convexgeometry
Author: Joseph Anderson
Author-email: jtanderson@salisbury.edu
License: UNKNOWN
Project-URL: Bug Tracker, https://github.com/jtanderson/convexgeometry/issues
Platform: UNKNOWN
Classifier: Programming Language :: Python :: 3
Classifier: License :: OSI Approved :: MIT License
Classifier: Operating System :: OS Independent
Requires-Python: >=3.6
